multiaddr/__init__.py
multiaddr/codec.py
multiaddr/multiaddr.py
multiaddr/protocols.py
multiaddr/util.py
py_multiaddr-0.0.3.dist-info/AUTHORS
py_multiaddr-0.0.3.dist-info/LICENSE
py_multiaddr-0.0.3.dist-info/METADATA
py_multiaddr-0.0.3.dist-info/WHEEL
py_multiaddr-0.0.3.dist-info/top_level.txt
py_multiaddr-0.0.3.dist-info/RECORD
