Metadata-Version: 2.1
Name: py-multiaddr
Version: 0.0.3
Summary: Python implementation of jbenet's multiaddr
Home-page: https://github.com/sbuss/multiaddr
Author: Steven Buss
Author-email: steven.buss@gmail.com
License: MIT License
Download-URL: https://github.com/sbuss/multiaddr/tarball/0.0.3
Keywords: multiaddr
Platform: UNKNOWN
Classifier: Development Status :: 2 - Pre-Alpha
Classifier: Intended Audience :: Developers
Classifier: License :: OSI Approved :: MIT License
Classifier: Natural Language :: English
Classifier: Programming Language :: Python :: 2
Classifier: Programming Language :: Python :: 2.6
Classifier: Programming Language :: Python :: 2.7
Classifier: Programming Language :: Python :: 3
Classifier: Programming Language :: Python :: 3.3
Classifier: Programming Language :: Python :: 3.4
Classifier: Programming Language :: Python :: 3.5
Requires-Dist: varint
Requires-Dist: six
Requires-Dist: base58
Requires-Dist: netaddr
